CORBA.py
CosNaming_idl.py
PortableServer.py
PortableServer__POA.py
_omniConnMgmt.cpython-310-aarch64-linux-gnu.so
_omniConnMgmt.cpython-310-aarch64-linux-gnu.so.4
_omniConnMgmt.cpython-310-aarch64-linux-gnu.so.4.3
_omniZIOP.cpython-310-aarch64-linux-gnu.so
_omniZIOP.cpython-310-aarch64-linux-gnu.so.4
_omniZIOP.cpython-310-aarch64-linux-gnu.so.4.3
_omnicodesets.cpython-310-aarch64-linux-gnu.so
_omnicodesets.cpython-310-aarch64-linux-gnu.so.4
_omnicodesets.cpython-310-aarch64-linux-gnu.so.4.3
_omniidl.cpython-310-aarch64-linux-gnu.so
_omniidl.cpython-310-aarch64-linux-gnu.so.4
_omniidl.cpython-310-aarch64-linux-gnu.so.4.3
_omnipy.cpython-310-aarch64-linux-gnu.so
_omnipy.cpython-310-aarch64-linux-gnu.so.4
_omnipy.cpython-310-aarch64-linux-gnu.so.4.3
CosNaming/__init__.py
CosNaming__POA/__init__.py
jeteve_omniorb/__init__.py
jeteve_omniorb/wrapper.py
jeteve_omniorb/bin/catior
jeteve_omniorb/bin/convertior
jeteve_omniorb/bin/genior
jeteve_omniorb/bin/nameclt
jeteve_omniorb/bin/omkdepend
jeteve_omniorb/bin/omniMapper
jeteve_omniorb/bin/omniNames
jeteve_omniorb/bin/omnicpp
jeteve_omniorb/bin/omniidl
jeteve_omniorb/bin/omniidlrun.py
jeteve_omniorb.libs/libomniCodeSets4-3c65b363.so.3.3
jeteve_omniorb.libs/libomniConnectionMgmt4-7d67c56c.so.3.3
jeteve_omniorb.libs/libomniORB4-7dbd8510.so.3.3
jeteve_omniorb.libs/libomniZIOP4-47511f48.so.3.3
jeteve_omniorb.libs/libomnithread-656ad94d.so.4.3
omniORB/BiDirPolicy.py
omniORB/CORBA.py
omniORB/Compression.py
omniORB/ConnectionInfo.py
omniORB/PortableServer.py
omniORB/PortableServer__POA.py
omniORB/URI.py
omniORB/ZIOP.py
omniORB/__init__.py
omniORB/ami.py
omniORB/any.py
omniORB/boxes_idl.py
omniORB/codesets.py
omniORB/compression_idl.py
omniORB/corbaidl_idl.py
omniORB/httpCrypto.py
omniORB/interceptors.py
omniORB/ir_idl.py
omniORB/messaging_idl.py
omniORB/minorCodes.py
omniORB/omniConnectionMgmt.py
omniORB/omniPolicy.py
omniORB/omniZIOP.py
omniORB/pollable_idl.py
jeteve_omniorb-4.3.3.post6.dist-info/METADATA
jeteve_omniorb-4.3.3.post6.dist-info/WHEEL
jeteve_omniorb-4.3.3.post6.dist-info/entry_points.txt
jeteve_omniorb-4.3.3.post6.dist-info/top_level.txt
jeteve_omniorb-4.3.3.post6.dist-info/RECORD
jeteve_omniorb-4.3.3.post6.dist-info/licenses/LICENSE.txt
