Metadata-Version: 2.4
Name: jeteve-omniorb
Version: 4.3.3.post6
Summary: pypi compatible packaging for OmniORB 4.3.3
Author-email: Jerome Eteve <jerome.eteve@gmail.com>
License: MIT
Project-URL: Documentation, https://github.com/jeteve/jeteve-omniorb#readme
Project-URL: Issues, https://github.com/jeteve/jeteve-omniorb/issues
Project-URL: Source, https://github.com/jeteve/jeteve-omniorb
Classifier: Development Status :: 4 - Beta
Classifier: Programming Language :: Python
Classifier: Programming Language :: Python :: Implementation :: CPython
Classifier: Topic :: Software Development :: Libraries
Classifier: Topic :: Software Development :: Object Brokering
Classifier: Topic :: Software Development :: Object Brokering :: CORBA
Requires-Python: >=3.8
License-File: LICENSE.txt
Dynamic: license-file
